kxy/__init__.py
kxy/framework/DailyRotatingFileHandler.py
kxy/framework/__init__.py
kxy/framework/__logger.py
kxy/framework/auto_register.py
kxy/framework/base_config.py
kxy/framework/base_dal.py
kxy/framework/base_entity.py
kxy/framework/base_service.py
kxy/framework/config_manager.py
kxy/framework/context.py
kxy/framework/date_util.py
kxy/framework/delete_safe_list.py
kxy/framework/filter.py
kxy/framework/filter_department.py
kxy/framework/filter_tenant.py
kxy/framework/filter_user.py
kxy/framework/friendly_exception.py
kxy/framework/func.py
kxy/framework/generat_contact.py
kxy/framework/hettp_client.py
kxy/framework/http_client.py
kxy/framework/id_generator.py
kxy/framework/ignor_filter.py
kxy/framework/kxy_logger.py
kxy/framework/kxy_logger_filter.py
kxy/framework/logger.py
kxy/framework/mapper.py
kxy/framework/redis_client.py
kxy/framework/result.py
kxy/framework/slogger.py
kxy/framework/util.py
kxy-framework/__init__.py
kxy-framework/base_config.py
kxy-framework/base_dal.py
kxy-framework/base_entity.py
kxy-framework/base_service.py
kxy-framework/friendly_exception.py
kxy-framework/mapper.py
simple_util/DailyRotatingFileHandler.py
simple_util/__init__.py
simple_util/ckquery.py
simple_util/date_util.py
simple_util/delete_safe_list.py
simple_util/harbor_api.py
simple_util/id_generator.py
simple_util/slogger.py
simple_util/util.py
test/TestSnowflakeIDGenerator.py
test/__init__.py
test/config.py
test/testLogger.py
test/testRedis.py
test/testUtil.py
test/test_framework.py
test/test_table.py
test/test_table_api.py
test/test_table_dal.py
kxy_framework-1.4.13.dist-info/METADATA
kxy_framework-1.4.13.dist-info/WHEEL
kxy_framework-1.4.13.dist-info/top_level.txt
kxy_framework-1.4.13.dist-info/RECORD
