Metadata-Version: 2.1
Name: kxy-framework
Version: 1.4.13
Summary: 封装了ORM框架
Home-page: https://pypi.org/project/kxy-framework/
Author: Johnliu
Author-email: 1242108463@qq.com
License: MIT
Platform: UNKNOWN
Classifier: Development Status :: 3 - Alpha
Classifier: Intended Audience :: Developers
Classifier: License :: OSI Approved :: MIT License
Classifier: Programming Language :: Python
Classifier: Programming Language :: Python :: 3.7
Requires-Dist: SQLAlchemy>=2.0.38
Requires-Dist: aiomysql>=0.2.0
Requires-Dist: fastapi>=0.115.8
Requires-Dist: httpx>=0.28.1
Requires-Dist: python-jose>=3.4.0
Requires-Dist: redis>=5.2.1
